Metadata-Version: 2.2
Name: modulee
Version: 1.0
Summary: Hatha vajra
Author: Sneha k
Dynamic: author
Dynamic: summary
